{
  "autoEquip": [
    {
      "item1": 3052,
      "item2": 3089,
      "on": false,
      "title": "Auto Equip",
      "slot": 9
    },
    {
      "item1": 0,
      "item2": 0,
      "on": false,
      "title": "Auto Equip",
      "slot": 0
    }
  ],
  "BotServerChannel": "5763954330186",
  "foodItems": [
    {
      "count": 1,
      "id": 3582
    },
    {
      "count": 1,
      "id": 3577
    },
    {
      "count": 1,
      "id": 3723
    },
    {
      "count": 1,
      "id": 3583
    },
    {
      "count": 1,
      "id": 3732
    },
    {
      "count": 1,
      "id": 3587
    },
    {
      "count": 1,
      "id": 3578
    }
  ],
  "alarms": {
    "ignoreFriends": [

    ],
    "flashClient": [

    ],
    "creatureDetected": [

    ],
    "damageTaken": [

    ],
    "playerDetected": [

    ],
    "creatureName": {
      "value": ""
    },
    "lowHealth": {
      "value": 20
    },
    "lowMana": {
      "value": 20
    },
    "playerAttack": [

    ],
    "privateMsg": [

    ],
    "defaultMsg": [

    ],
    "customMessage": {
      "value": ""
    }
  },
  "extras": {
    "suppliesControl": true,
    "reachable": true,
    "huntRoutes": 300,
    "height": 360,
    "stake": false,
    "talkDelay": 800,
    "holdWgHot": "F6",
    "timers": true,
    "rope": 3003,
    "holdMwHot": "F5",
    "separatePm": true,
    "reUse": false,
    "holdMwall": true,
    "autoOpenDoors": true,
    "title": false,
    "scythe": 3453,
    "highlightTarget": true,
    "nextBackpack": true,
    "lootDelay": 200,
    "killUnder": 1,
    "looting": 40,
    "gotoMaxDistance": 127,
    "bless": false,
    "checkPlayer": false,
    "pathfinding": true,
    "machete": 3308,
    "antiKick": true,
    "useAll": "space",
    "shovel": 3457,
    "lootLast": true,
    "joinBot": false,
    "oberon": true
  },
  "caveBot": {
    "backStop": false,
    "forceRefill": false,
    "backTrainers": false,
    "backOffline": false
  },
  "bestHit": 5082,
  "EquipperPanel": {
    "rules": [

    ],
    "bosses": [

    ],
    "enabled": false
  },
  "BOTserver": {
    "mwallInfo": true,
    "broadcasts": true,
    "mwalls": [

    ],
    "manaInfo": true,
    "vocation": true,
    "outfit": false
  },
  "newHealer": {
    "enabled": false,
    "customPlayers": [

    ],
    "groups": [

    ],
    "settings": [
      {
        "value": 268,
        "text": "Mana Item ",
        "type": "HealItem"
      },
      {
        "value": 6,
        "text": "Item Range: ",
        "type": "HealScroll"
      },
      {
        "value": 3160,
        "text": "Health Item ",
        "type": "HealItem"
      },
      {
        "value": 2,
        "text": "Mas Res Players: ",
        "type": "HealScroll"
      },
      {
        "value": 80,
        "text": "Heal Friend at: ",
        "type": "HealScroll"
      },
      {
        "value": 80,
        "text": "Use Gran Sio at: ",
        "type": "HealScroll"
      },
      {
        "value": 80,
        "text": "Min Player HP%: ",
        "type": "HealScroll"
      },
      {
        "value": 50,
        "text": "Min Player MP%: ",
        "type": "HealScroll"
      }
    ],
    "vocations": [

    ],
    "priorities": [
      {
        "custom": true,
        "enabled": false,
        "name": "Custom Spell"
      },
      {
        "strong": true,
        "enabled": true,
        "name": "Exura Gran Sio"
      },
      {
        "enabled": true,
        "normal": true,
        "name": "Exura Sio"
      },
      {
        "area": true,
        "enabled": true,
        "name": "Exura Gran Mas Res"
      },
      {
        "health": true,
        "enabled": true,
        "name": "Health Item"
      },
      {
        "enabled": true,
        "mana": true,
        "name": "Mana Item"
      }
    ],
    "conditions": {
      "knights": true,
      "paladins": true,
      "party": true,
      "sorcerers": false,
      "druids": false,
      "guild": false,
      "botserver": false,
      "friends": false
    }
  },
  "pushmax": {
    "pushMaxRuneId": 3188,
    "enabled": false,
    "pushMaxKey": "PageUp",
    "pushDelay": 1060,
    "mwallBlockId": 2128
  },
  "cavebotSell": [

  ],
  "bestHeal": 4027,
  "autoTradeMessage": "I'm using OTClientV8!",
  "caveBotTasker": {
    "taskName": "",
    "inProgress": false,
    "count": 0,
    "max": 0,
    "monster": ""
  },
  "specialDeposit": {
    "last": false,
    "height": 380,
    "items": [

    ]
  },
  "analyzers": {
    "rarityFrames": true,
    "trackedBoss": [

    ],
    "outfits": {
      "Gnarlhound": {
        "addons": 0,
        "feet": 0,
        "legs": 0,
        "aura": 0,
        "head": 0,
        "type": 341,
        "auxType": 0,
        "body": 0,
        "mount": 0
      },
      "Gazer": {
        "addons": 0,
        "feet": 0,
        "legs": 0,
        "aura": 0,
        "head": 0,
        "type": 109,
        "auxType": 0,
        "body": 0,
        "mount": 0
      },
      "Death Blob": {
        "addons": 0,
        "feet": 0,
        "legs": 0,
        "aura": 0,
        "head": 0,
        "type": 315,
        "auxType": 0,
        "body": 0,
        "mount": 0
      },
      "Diremaw": {
        "addons": 0,
        "feet": 0,
        "legs": 0,
        "aura": 0,
        "head": 0,
        "type": 1034,
        "auxType": 0,
        "body": 0,
        "mount": 0
      },
      "Scorpion": {
        "addons": 0,
        "feet": 0,
        "legs": 0,
        "aura": 0,
        "head": 0,
        "type": 43,
        "auxType": 0,
        "body": 0,
        "mount": 0
      },
      "Wasp": {
        "addons": 0,
        "feet": 0,
        "legs": 0,
        "aura": 0,
        "head": 0,
        "type": 44,
        "auxType": 0,
        "body": 0,
        "mount": 0
      },
      "Orc Trainer": {
        "addons": 0,
        "feet": 0,
        "legs": 0,
        "aura": 0,
        "head": 0,
        "type": 5,
        "auxType": 0,
        "body": 0,
        "mount": 0
      },
      "Terramite": {
        "addons": 0,
        "feet": 0,
        "legs": 0,
        "aura": 0,
        "head": 0,
        "type": 346,
        "auxType": 0,
        "body": 0,
        "mount": 0
      },
      "Goblin Assassin": {
        "addons": 0,
        "feet": 0,
        "legs": 0,
        "aura": 0,
        "head": 0,
        "type": 296,
        "auxType": 0,
        "body": 0,
        "mount": 0
      },
      "Spitter": {
        "addons": 0,
        "feet": 0,
        "legs": 0,
        "aura": 0,
        "head": 0,
        "type": 461,
        "auxType": 0,
        "body": 0,
        "mount": 0
      },
      "Deepling Brawler": {
        "addons": 0,
        "feet": 0,
        "legs": 0,
        "body": 0,
        "head": 0,
        "type": 470,
        "auxType": 0,
        "aura": 0,
        "mount": 0
      },
      "Hellflayer": {
        "addons": 0,
        "feet": 0,
        "legs": 0,
        "aura": 0,
        "head": 0,
        "type": 856,
        "auxType": 0,
        "body": 0,
        "mount": 0
      },
      "Hide": {
        "addons": 0,
        "feet": 0,
        "legs": 0,
        "aura": 0,
        "head": 0,
        "type": 219,
        "auxType": 0,
        "body": 0,
        "mount": 0
      },
      "Dreadwing": {
        "addons": 0,
        "feet": 0,
        "legs": 0,
        "aura": 0,
        "head": 0,
        "type": 307,
        "auxType": 0,
        "body": 0,
        "mount": 0
      },
      "Wereboar": {
        "addons": 0,
        "feet": 0,
        "legs": 0,
        "aura": 0,
        "head": 0,
        "type": 721,
        "auxType": 0,
        "body": 0,
        "mount": 0
      },
      "Dark Apprentice": {
        "addons": 1,
        "feet": 115,
        "legs": 95,
        "aura": 0,
        "head": 78,
        "type": 133,
        "auxType": 0,
        "body": 57,
        "mount": 0
      },
      "Thornback Tortoise": {
        "addons": 0,
        "feet": 0,
        "legs": 0,
        "aura": 0,
        "head": 0,
        "type": 198,
        "auxType": 0,
        "body": 0,
        "mount": 0
      },
      "Hero": {
        "addons": 0,
        "feet": 0,
        "legs": 0,
        "aura": 0,
        "head": 0,
        "type": 73,
        "auxType": 0,
        "body": 0,
        "mount": 0
      },
      "Nightmare Scion": {
        "addons": 0,
        "feet": 0,
        "legs": 0,
        "aura": 0,
        "head": 0,
        "type": 321,
        "auxType": 0,
        "body": 0,
        "mount": 0
      },
      "Cyclops": {
        "addons": 0,
        "feet": 0,
        "legs": 0,
        "aura": 0,
        "head": 0,
        "type": 22,
        "auxType": 0,
        "body": 0,
        "mount": 0
      },
      "Cult Believer": {
        "addons": 1,
        "feet": 57,
        "legs": 39,
        "aura": 0,
        "head": 98,
        "type": 132,
        "auxType": 0,
        "body": 77,
        "mount": 0
      },
      "Dark Magician": {
        "addons": 2,
        "feet": 132,
        "legs": 50,
        "aura": 0,
        "head": 116,
        "type": 133,
        "auxType": 0,
        "body": 95,
        "mount": 0
      },
      "Hunter": {
        "addons": 0,
        "feet": 115,
        "legs": 121,
        "aura": 0,
        "head": 95,
        "type": 129,
        "auxType": 0,
        "body": 116,
        "mount": 0
      },
      "Chakoya Toolshaper": {
        "addons": 0,
        "feet": 0,
        "legs": 0,
        "aura": 0,
        "head": 0,
        "type": 259,
        "auxType": 0,
        "body": 0,
        "mount": 0
      },
      "Silencer": {
        "addons": 0,
        "feet": 0,
        "legs": 0,
        "aura": 0,
        "head": 0,
        "type": 585,
        "auxType": 0,
        "body": 0,
        "mount": 0
      },
      "Black Knight Trainer": {
        "addons": 3,
        "feet": 95,
        "legs": 95,
        "aura": 0,
        "head": 95,
        "type": 131,
        "auxType": 0,
        "body": 95,
        "mount": 0
      },
      "Doomhowl": {
        "addons": 0,
        "feet": 0,
        "legs": 0,
        "aura": 0,
        "head": 0,
        "type": 308,
        "auxType": 0,
        "body": 0,
        "mount": 0
      },
      "Barbarian Headsplitter": {
        "addons": 0,
        "feet": 132,
        "legs": 119,
        "aura": 0,
        "head": 115,
        "type": 253,
        "auxType": 0,
        "body": 105,
        "mount": 0
      },
      "Dragon Hatchling": {
        "addons": 0,
        "feet": 0,
        "legs": 0,
        "aura": 0,
        "head": 0,
        "type": 271,
        "auxType": 0,
        "body": 0,
        "mount": 0
      },
      "Monk": {
        "addons": 0,
        "feet": 0,
        "legs": 0,
        "aura": 0,
        "head": 0,
        "type": 57,
        "auxType": 0,
        "body": 0,
        "mount": 0
      },
      "Vile Grandmaster": {
        "addons": 1,
        "feet": 94,
        "legs": 95,
        "aura": 0,
        "head": 97,
        "type": 268,
        "auxType": 0,
        "body": 0,
        "mount": 0
      },
      "Werebear": {
        "addons": 0,
        "feet": 0,
        "legs": 0,
        "aura": 0,
        "head": 0,
        "type": 720,
        "auxType": 0,
        "body": 0,
        "mount": 0
      },
      "Crimson Frog": {
        "addons": 0,
        "feet": 78,
        "legs": 94,
        "aura": 0,
        "head": 94,
        "type": 226,
        "auxType": 0,
        "body": 78,
        "mount": 0
      },
      "Penguin": {
        "addons": 0,
        "feet": 0,
        "legs": 0,
        "aura": 0,
        "head": 0,
        "type": 250,
        "auxType": 0,
        "body": 0,
        "mount": 0
      },
      "Sight of Surrender": {
        "addons": 0,
        "feet": 0,
        "legs": 0,
        "aura": 0,
        "head": 0,
        "type": 583,
        "auxType": 0,
        "body": 0,
        "mount": 0
      },
      "Behemoth Trainer": {
        "addons": 0,
        "feet": 0,
        "legs": 0,
        "aura": 0,
        "head": 0,
        "type": 55,
        "auxType": 0,
        "body": 0,
        "mount": 0
      },
      "Rocko": {
        "addons": 0,
        "feet": 0,
        "legs": 0,
        "aura": 0,
        "head": 0,
        "type": 67,
        "auxType": 0,
        "body": 0,
        "mount": 0
      },
      "Brutal Crocodile": {
        "addons": 0,
        "feet": 0,
        "legs": 0,
        "aura": 0,
        "head": 0,
        "type": 119,
        "auxType": 0,
        "body": 0,
        "mount": 0
      },
      "Minotaur Guard": {
        "addons": 0,
        "feet": 0,
        "legs": 0,
        "aura": 0,
        "head": 0,
        "type": 29,
        "auxType": 0,
        "body": 0,
        "mount": 0
      },
      "Grim Reaper": {
        "addons": 0,
        "feet": 0,
        "legs": 0,
        "aura": 0,
        "head": 0,
        "type": 300,
        "auxType": 0,
        "body": 0,
        "mount": 0
      },
      "Kollos": {
        "addons": 0,
        "feet": 0,
        "legs": 0,
        "aura": 0,
        "head": 0,
        "type": 458,
        "auxType": 0,
        "body": 0,
        "mount": 0
      },
      "Nomad": {
        "addons": 2,
        "feet": 2,
        "legs": 22,
        "aura": 0,
        "head": 114,
        "type": 146,
        "auxType": 0,
        "body": 20,
        "mount": 0
      },
      "Shardhead": {
        "addons": 0,
        "feet": 0,
        "legs": 0,
        "aura": 0,
        "head": 0,
        "type": 261,
        "auxType": 0,
        "body": 0,
        "mount": 0
      },
      "Goblin Scavenger": {
        "addons": 0,
        "feet": 0,
        "legs": 0,
        "aura": 0,
        "head": 0,
        "type": 297,
        "auxType": 0,
        "body": 0,
        "mount": 0
      },
      "Quara Constrictor Scout": {
        "addons": 0,
        "feet": 0,
        "legs": 0,
        "aura": 0,
        "head": 0,
        "type": 46,
        "auxType": 0,
        "body": 0,
        "mount": 0
      },
      "The Welter": {
        "addons": 0,
        "feet": 0,
        "legs": 0,
        "aura": 0,
        "head": 0,
        "type": 563,
        "auxType": 0,
        "body": 0,
        "mount": 0
      },
      "Frost Giant": {
        "addons": 0,
        "feet": 0,
        "legs": 0,
        "aura": 0,
        "head": 0,
        "type": 257,
        "auxType": 0,
        "body": 0,
        "mount": 0
      },
      "Minotaur Mage": {
        "addons": 0,
        "feet": 0,
        "legs": 0,
        "aura": 0,
        "head": 0,
        "type": 23,
        "auxType": 0,
        "body": 0,
        "mount": 0
      },
      "Shard Of Corruption": {
        "addons": 0,
        "feet": 0,
        "legs": 0,
        "aura": 0,
        "head": 0,
        "type": 67,
        "auxType": 0,
        "body": 0,
        "mount": 0
      },
      "Dawnfire Asura": {
        "addons": 1,
        "feet": 79,
        "legs": 78,
        "aura": 0,
        "head": 114,
        "type": 150,
        "auxType": 0,
        "body": 94,
        "mount": 0
      },
      "Lizard Snakecharmer": {
        "addons": 0,
        "feet": 0,
        "legs": 0,
        "aura": 0,
        "head": 0,
        "type": 115,
        "auxType": 0,
        "body": 0,
        "mount": 0
      },
      "Orc Warrior": {
        "addons": 0,
        "feet": 0,
        "legs": 0,
        "aura": 0,
        "head": 0,
        "type": 7,
        "auxType": 0,
        "body": 0,
        "mount": 0
      },
      "Mujina": {
        "addons": 0,
        "feet": 0,
        "legs": 0,
        "aura": 0,
        "head": 0,
        "type": 309,
        "auxType": 0,
        "body": 0,
        "mount": 0
      },
      "Crab": {
        "addons": 0,
        "feet": 0,
        "legs": 0,
        "aura": 0,
        "head": 0,
        "type": 112,
        "auxType": 0,
        "body": 0,
        "mount": 0
      },
      "The Old Widow": {
        "addons": 0,
        "feet": 0,
        "legs": 0,
        "aura": 0,
        "head": 0,
        "type": 208,
        "auxType": 0,
        "body": 0,
        "mount": 0
      },
      "Quara Hydromancer Scout": {
        "addons": 0,
        "feet": 0,
        "legs": 0,
        "aura": 0,
        "head": 0,
        "type": 47,
        "auxType": 0,
        "body": 0,
        "mount": 0
      },
      "Mammoth": {
        "addons": 0,
        "feet": 0,
        "legs": 0,
        "aura": 0,
        "head": 0,
        "type": 199,
        "auxType": 0,
        "body": 0,
        "mount": 0
      },
      "Barbarian Bloodwalker": {
        "addons": 0,
        "feet": 132,
        "legs": 132,
        "aura": 0,
        "head": 114,
        "type": 255,
        "auxType": 0,
        "body": 132,
        "mount": 0
      },
      "Demon": {
        "addons": 0,
        "feet": 0,
        "legs": 0,
        "aura": 0,
        "head": 0,
        "type": 35,
        "auxType": 0,
        "body": 0,
        "mount": 0
      },
      "Feverish Citizen": {
        "addons": 0,
        "feet": 0,
        "legs": 0,
        "aura": 0,
        "head": 0,
        "type": 425,
        "auxType": 0,
        "body": 0,
        "mount": 0
      },
      "Haunter": {
        "addons": 0,
        "feet": 0,
        "legs": 0,
        "aura": 0,
        "head": 0,
        "type": 320,
        "auxType": 0,
        "body": 0,
        "mount": 0
      },
      "Amazon": {
        "addons": 0,
        "feet": 115,
        "legs": 95,
        "aura": 0,
        "head": 113,
        "type": 137,
        "auxType": 0,
        "body": 120,
        "mount": 0
      },
      "Goblin Leader": {
        "addons": 0,
        "feet": 0,
        "legs": 0,
        "aura": 0,
        "head": 0,
        "type": 61,
        "auxType": 0,
        "body": 0,
        "mount": 0
      },
      "Slime": {
        "addons": 0,
        "feet": 0,
        "legs": 0,
        "aura": 0,
        "head": 0,
        "type": 19,
        "auxType": 0,
        "body": 0,
        "mount": 0
      },
      "Cave Rat": {
        "addons": 0,
        "feet": 0,
        "legs": 0,
        "aura": 0,
        "head": 0,
        "type": 56,
        "auxType": 0,
        "body": 0,
        "mount": 0
      },
      "Dragon": {
        "addons": 0,
        "feet": 0,
        "legs": 0,
        "aura": 0,
        "head": 0,
        "type": 34,
        "auxType": 0,
        "body": 0,
        "mount": 0
      },
      "Elephant": {
        "addons": 0,
        "feet": 0,
        "legs": 0,
        "aura": 0,
        "head": 0,
        "type": 211,
        "auxType": 0,
        "body": 0,
        "mount": 0
      },
      "Stone Golem": {
        "addons": 0,
        "feet": 0,
        "legs": 0,
        "aura": 0,
        "head": 0,
        "type": 67,
        "auxType": 0,
        "body": 0,
        "mount": 0
      },
      "Crypt Shambler": {
        "addons": 0,
        "feet": 0,
        "legs": 0,
        "aura": 0,
        "head": 0,
        "type": 100,
        "auxType": 0,
        "body": 0,
        "mount": 0
      },
      "Devourer": {
        "addons": 0,
        "feet": 0,
        "legs": 0,
        "aura": 0,
        "head": 0,
        "type": 617,
        "auxType": 0,
        "body": 0,
        "mount": 0
      },
      "Dwarf": {
        "addons": 0,
        "feet": 0,
        "legs": 0,
        "aura": 0,
        "head": 0,
        "type": 69,
        "auxType": 0,
        "body": 0,
        "mount": 0
      },
      "Tortoise": {
        "addons": 0,
        "feet": 0,
        "legs": 0,
        "aura": 0,
        "head": 0,
        "type": 197,
        "auxType": 0,
        "body": 0,
        "mount": 0
      },
      "Gladiator": {
        "addons": 0,
        "feet": 114,
        "legs": 79,
        "aura": 0,
        "head": 78,
        "type": 131,
        "auxType": 0,
        "body": 3,
        "mount": 0
      },
      "Valkyrie": {
        "addons": 0,
        "feet": 96,
        "legs": 95,
        "aura": 0,
        "head": 113,
        "type": 139,
        "auxType": 0,
        "body": 38,
        "mount": 0
      },
      "Crawler": {
        "addons": 0,
        "feet": 0,
        "legs": 0,
        "aura": 0,
        "head": 0,
        "type": 456,
        "auxType": 0,
        "body": 0,
        "mount": 0
      },
      "Lizard Sentinel": {
        "addons": 0,
        "feet": 0,
        "legs": 0,
        "aura": 0,
        "head": 0,
        "type": 114,
        "auxType": 0,
        "body": 0,
        "mount": 0
      },
      "Bug": {
        "addons": 0,
        "feet": 0,
        "legs": 0,
        "aura": 0,
        "head": 0,
        "type": 45,
        "auxType": 0,
        "body": 0,
        "mount": 0
      },
      "Badger": {
        "addons": 0,
        "feet": 0,
        "legs": 0,
        "aura": 0,
        "head": 0,
        "type": 105,
        "auxType": 0,
        "body": 0,
        "mount": 0
      },
      "Witch": {
        "addons": 0,
        "feet": 0,
        "legs": 0,
        "aura": 0,
        "head": 0,
        "type": 54,
        "auxType": 0,
        "body": 0,
        "mount": 0
      },
      "Mafuteromalo": {
        "addons": 0,
        "feet": 0,
        "legs": 0,
        "aura": 0,
        "head": 20,
        "type": 241,
        "auxType": 0,
        "body": 0,
        "mount": 0
      },
      "Tirecz": {
        "addons": 0,
        "feet": 0,
        "legs": 0,
        "aura": 0,
        "head": 0,
        "type": 334,
        "auxType": 0,
        "body": 0,
        "mount": 0
      },
      "Demon Skeleton": {
        "addons": 0,
        "feet": 0,
        "legs": 0,
        "aura": 0,
        "head": 0,
        "type": 37,
        "auxType": 0,
        "body": 0,
        "mount": 0
      },
      "Gang Member": {
        "addons": 0,
        "feet": 20,
        "legs": 42,
        "aura": 0,
        "head": 114,
        "type": 151,
        "auxType": 0,
        "body": 19,
        "mount": 0
      },
      "Werefox": {
        "addons": 0,
        "feet": 0,
        "legs": 0,
        "aura": 0,
        "head": 0,
        "type": 1030,
        "auxType": 0,
        "body": 0,
        "mount": 0
      },
      "Werebadger": {
        "addons": 0,
        "feet": 0,
        "legs": 0,
        "aura": 0,
        "head": 0,
        "type": 729,
        "auxType": 0,
        "body": 0,
        "mount": 0
      },
      "Behemoth": {
        "addons": 0,
        "feet": 0,
        "legs": 0,
        "aura": 0,
        "head": 0,
        "type": 55,
        "auxType": 0,
        "body": 0,
        "mount": 0
      },
      "Skeleton": {
        "addons": 0,
        "feet": 0,
        "legs": 0,
        "aura": 0,
        "head": 0,
        "type": 33,
        "auxType": 0,
        "body": 0,
        "mount": 0
      },
      "Vexclaw": {
        "addons": 0,
        "feet": 0,
        "legs": 0,
        "aura": 0,
        "head": 0,
        "type": 854,
        "auxType": 0,
        "body": 0,
        "mount": 0
      },
      "War Wolf": {
        "addons": 0,
        "feet": 0,
        "legs": 0,
        "aura": 0,
        "head": 0,
        "type": 3,
        "auxType": 0,
        "body": 0,
        "mount": 0
      },
      "Menace": {
        "addons": 0,
        "feet": 0,
        "legs": 0,
        "aura": 0,
        "head": 0,
        "type": 113,
        "auxType": 0,
        "body": 0,
        "mount": 0
      },
      "Wyrm": {
        "addons": 0,
        "feet": 0,
        "legs": 0,
        "aura": 0,
        "head": 0,
        "type": 291,
        "auxType": 0,
        "body": 0,
        "mount": 0
      },
      "Clomp": {
        "addons": 0,
        "feet": 0,
        "legs": 0,
        "aura": 0,
        "head": 0,
        "type": 860,
        "auxType": 0,
        "body": 0,
        "mount": 0
      },
      "Glooth Blob": {
        "addons": 0,
        "feet": 0,
        "legs": 0,
        "aura": 0,
        "head": 0,
        "type": 614,
        "auxType": 0,
        "body": 0,
        "mount": 0
      },
      "Ogre Brute": {
        "addons": 0,
        "feet": 0,
        "legs": 0,
        "aura": 0,
        "head": 0,
        "type": 857,
        "auxType": 0,
        "body": 0,
        "mount": 0
      },
      "Water Elemental": {
        "addons": 0,
        "feet": 0,
        "legs": 0,
        "aura": 0,
        "head": 0,
        "type": 286,
        "auxType": 0,
        "body": 0,
        "mount": 0
      },
      "Poacher": {
        "addons": 1,
        "feet": 115,
        "legs": 119,
        "aura": 0,
        "head": 115,
        "type": 129,
        "auxType": 0,
        "body": 119,
        "mount": 0
      },
      "Brutal Killer Caiman": {
        "addons": 0,
        "feet": 0,
        "legs": 0,
        "aura": 0,
        "head": 0,
        "type": 358,
        "auxType": 0,
        "body": 0,
        "mount": 0
      },
      "Bog Raider": {
        "addons": 0,
        "feet": 0,
        "legs": 0,
        "aura": 0,
        "head": 0,
        "type": 299,
        "auxType": 0,
        "body": 0,
        "mount": 0
      },
      "Panda": {
        "addons": 0,
        "feet": 0,
        "legs": 0,
        "aura": 0,
        "head": 0,
        "type": 123,
        "auxType": 0,
        "body": 0,
        "mount": 0
      },
      "Souleater": {
        "addons": 0,
        "feet": 0,
        "legs": 0,
        "aura": 0,
        "head": 0,
        "type": 355,
        "auxType": 0,
        "body": 0,
        "mount": 0
      },
      "Blood Crab": {
        "addons": 0,
        "feet": 0,
        "legs": 0,
        "aura": 0,
        "head": 0,
        "type": 200,
        "auxType": 0,
        "body": 0,
        "mount": 0
      },
      "Glooth Brigand": {
        "addons": 0,
        "feet": 114,
        "legs": 107,
        "aura": 0,
        "head": 114,
        "type": 137,
        "auxType": 0,
        "body": 114,
        "mount": 0
      },
      "Winter Wolf": {
        "addons": 0,
        "feet": 0,
        "legs": 0,
        "aura": 0,
        "head": 0,
        "type": 52,
        "auxType": 0,
        "body": 0,
        "mount": 0
      },
      "Dwarf Soldier": {
        "addons": 0,
        "feet": 0,
        "legs": 0,
        "aura": 0,
        "head": 0,
        "type": 71,
        "auxType": 0,
        "body": 0,
        "mount": 0
      },
      "Skunk Trainer": {
        "addons": 0,
        "feet": 0,
        "legs": 0,
        "aura": 0,
        "head": 0,
        "type": 106,
        "auxType": 0,
        "body": 0,
        "mount": 0
      },
      "Wailing Widow": {
        "addons": 0,
        "feet": 0,
        "legs": 0,
        "aura": 0,
        "head": 0,
        "type": 347,
        "auxType": 0,
        "body": 0,
        "mount": 0
      },
      "Lizard High Guard": {
        "addons": 0,
        "feet": 0,
        "legs": 0,
        "aura": 0,
        "head": 0,
        "type": 337,
        "auxType": 0,
        "body": 0,
        "mount": 0
      },
      "Ice Golem": {
        "addons": 0,
        "feet": 0,
        "legs": 0,
        "aura": 0,
        "head": 0,
        "type": 261,
        "auxType": 0,
        "body": 0,
        "mount": 0
      },
      "Hydra": {
        "addons": 0,
        "feet": 0,
        "legs": 0,
        "aura": 0,
        "head": 0,
        "type": 121,
        "auxType": 0,
        "body": 0,
        "mount": 0
      },
      "Young Sea Serpent": {
        "addons": 0,
        "feet": 0,
        "legs": 0,
        "aura": 0,
        "head": 0,
        "type": 317,
        "auxType": 0,
        "body": 0,
        "mount": 0
      },
      "Cyclops Drone": {
        "addons": 0,
        "feet": 0,
        "legs": 0,
        "aura": 0,
        "head": 0,
        "type": 280,
        "auxType": 0,
        "body": 0,
        "mount": 0
      },
      "Faun": {
        "addons": 0,
        "feet": 81,
        "legs": 114,
        "aura": 0,
        "head": 81,
        "type": 980,
        "auxType": 0,
        "body": 115,
        "mount": 0
      },
      "Lion": {
        "addons": 0,
        "feet": 0,
        "legs": 0,
        "aura": 0,
        "head": 0,
        "type": 41,
        "auxType": 0,
        "body": 0,
        "mount": 0
      },
      "Lizard Templar": {
        "addons": 0,
        "feet": 0,
        "legs": 0,
        "aura": 0,
        "head": 0,
        "type": 113,
        "auxType": 0,
        "body": 0,
        "mount": 0
      },
      "Poison Spider": {
        "addons": 0,
        "feet": 0,
        "legs": 0,
        "aura": 0,
        "head": 0,
        "type": 36,
        "auxType": 0,
        "body": 0,
        "mount": 0
      },
      "Orchid Frog": {
        "addons": 0,
        "feet": 114,
        "legs": 109,
        "aura": 0,
        "head": 109,
        "type": 226,
        "auxType": 0,
        "body": 14,
        "mount": 0
      },
      "Azure Frog": {
        "addons": 0,
        "feet": 66,
        "legs": 69,
        "aura": 0,
        "head": 69,
        "type": 226,
        "auxType": 0,
        "body": 66,
        "mount": 0
      },
      "Goblin": {
        "addons": 0,
        "feet": 0,
        "legs": 0,
        "aura": 0,
        "head": 0,
        "type": 61,
        "auxType": 0,
        "body": 0,
        "mount": 0
      },
      "Deepworm": {
        "addons": 0,
        "feet": 0,
        "legs": 0,
        "aura": 0,
        "head": 0,
        "type": 1033,
        "auxType": 0,
        "body": 0,
        "mount": 0
      },
      "Bandit": {
        "addons": 0,
        "feet": 114,
        "legs": 45,
        "aura": 0,
        "head": 58,
        "type": 129,
        "auxType": 0,
        "body": 59,
        "mount": 0
      },
      "Slim": {
        "addons": 0,
        "feet": 0,
        "legs": 0,
        "aura": 0,
        "head": 0,
        "type": 101,
        "auxType": 0,
        "body": 0,
        "mount": 0
      },
      "Rat": {
        "addons": 0,
        "feet": 0,
        "legs": 0,
        "aura": 0,
        "head": 0,
        "type": 21,
        "auxType": 0,
        "body": 0,
        "mount": 0
      },
      "Chakoya Windcaller": {
        "addons": 0,
        "feet": 0,
        "legs": 0,
        "aura": 0,
        "head": 0,
        "type": 260,
        "auxType": 0,
        "body": 0,
        "mount": 0
      },
      "Terror Bird": {
        "addons": 0,
        "feet": 0,
        "legs": 0,
        "aura": 0,
        "head": 0,
        "type": 218,
        "auxType": 0,
        "body": 0,
        "mount": 0
      },
      "Undead Gladiator": {
        "addons": 0,
        "feet": 0,
        "legs": 0,
        "aura": 0,
        "head": 0,
        "type": 306,
        "auxType": 0,
        "body": 0,
        "mount": 0
      },
      "Centipede": {
        "addons": 0,
        "feet": 0,
        "legs": 0,
        "aura": 0,
        "head": 0,
        "type": 124,
        "auxType": 0,
        "body": 0,
        "mount": 0
      },
      "Orc Spearman": {
        "addons": 0,
        "feet": 0,
        "legs": 0,
        "aura": 0,
        "head": 0,
        "type": 50,
        "auxType": 0,
        "body": 0,
        "mount": 0
      },
      "Wyvern": {
        "addons": 0,
        "feet": 0,
        "legs": 0,
        "aura": 0,
        "head": 0,
        "type": 239,
        "auxType": 0,
        "body": 0,
        "mount": 0
      },
      "Stampor": {
        "addons": 0,
        "feet": 0,
        "legs": 0,
        "aura": 0,
        "head": 0,
        "type": 381,
        "auxType": 0,
        "body": 0,
        "mount": 0
      },
      "Elf": {
        "addons": 0,
        "feet": 0,
        "legs": 0,
        "aura": 0,
        "head": 0,
        "type": 62,
        "auxType": 0,
        "body": 0,
        "mount": 0
      },
      "Dragon Lord": {
        "addons": 0,
        "feet": 0,
        "legs": 0,
        "aura": 0,
        "head": 0,
        "type": 39,
        "auxType": 0,
        "body": 0,
        "mount": 0
      },
      "Hyaena": {
        "addons": 0,
        "feet": 0,
        "legs": 0,
        "aura": 0,
        "head": 0,
        "type": 94,
        "auxType": 0,
        "body": 0,
        "mount": 0
      },
      "Minotaur Amazon": {
        "addons": 0,
        "feet": 0,
        "legs": 0,
        "aura": 0,
        "head": 0,
        "type": 608,
        "auxType": 0,
        "body": 0,
        "mount": 0
      },
      "Nightmare": {
        "addons": 0,
        "feet": 0,
        "legs": 0,
        "aura": 0,
        "head": 0,
        "type": 245,
        "auxType": 0,
        "body": 0,
        "mount": 0
      },
      "Execowtioner": {
        "addons": 0,
        "feet": 0,
        "legs": 0,
        "aura": 0,
        "head": 0,
        "type": 609,
        "auxType": 0,
        "body": 0,
        "mount": 0
      },
      "Dragon Lord Hatchling": {
        "addons": 0,
        "feet": 0,
        "legs": 0,
        "aura": 0,
        "head": 0,
        "type": 272,
        "auxType": 0,
        "body": 0,
        "mount": 0
      },
      "Avalanche": {
        "addons": 0,
        "feet": 0,
        "legs": 0,
        "aura": 0,
        "head": 0,
        "type": 261,
        "auxType": 0,
        "body": 0,
        "mount": 0
      },
      "Cat": {
        "addons": 0,
        "feet": 0,
        "legs": 0,
        "aura": 0,
        "head": 0,
        "type": 276,
        "auxType": 0,
        "body": 0,
        "mount": 0
      },
      "The Axeorcist": {
        "addons": 0,
        "feet": 0,
        "legs": 0,
        "aura": 0,
        "head": 0,
        "type": 8,
        "auxType": 0,
        "body": 0,
        "mount": 0
      },
      "Enslaved Dwarf": {
        "addons": 0,
        "feet": 0,
        "legs": 0,
        "body": 0,
        "head": 0,
        "type": 494,
        "auxType": 0,
        "aura": 0,
        "mount": 0
      },
      "Coldheart": {
        "addons": 0,
        "feet": 0,
        "legs": 0,
        "aura": 0,
        "head": 0,
        "type": 261,
        "auxType": 0,
        "body": 0,
        "mount": 0
      },
      "Plaguesmith": {
        "addons": 0,
        "feet": 0,
        "legs": 0,
        "aura": 0,
        "head": 0,
        "type": 247,
        "auxType": 0,
        "body": 0,
        "mount": 0
      },
      "Spider": {
        "addons": 0,
        "feet": 0,
        "legs": 0,
        "body": 0,
        "head": 0,
        "type": 30,
        "auxType": 0,
        "aura": 0,
        "mount": 0
      },
      "Cyclops Smith": {
        "addons": 0,
        "feet": 0,
        "legs": 0,
        "aura": 0,
        "head": 0,
        "type": 277,
        "auxType": 0,
        "body": 0,
        "mount": 0
      },
      "Mutated Rat": {
        "addons": 0,
        "feet": 0,
        "legs": 0,
        "aura": 0,
        "head": 0,
        "type": 305,
        "auxType": 0,
        "body": 0,
        "mount": 0
      },
      "Insectoid Worker": {
        "addons": 0,
        "feet": 0,
        "legs": 0,
        "aura": 0,
        "head": 0,
        "type": 403,
        "auxType": 0,
        "body": 0,
        "mount": 0
      },
      "Ice Witch": {
        "addons": 0,
        "feet": 105,
        "legs": 105,
        "aura": 0,
        "head": 0,
        "type": 149,
        "auxType": 0,
        "body": 47,
        "mount": 0
      },
      "Orc": {
        "addons": 0,
        "feet": 0,
        "legs": 0,
        "aura": 0,
        "head": 0,
        "type": 5,
        "auxType": 0,
        "body": 0,
        "mount": 0
      },
      "Ravenous Lava Lurker": {
        "addons": 0,
        "feet": 0,
        "legs": 0,
        "aura": 0,
        "head": 0,
        "type": 1041,
        "auxType": 0,
        "body": 0,
        "mount": 0
      },
      "starving wolf": {
        "addons": 0,
        "feet": 50,
        "legs": 40,
        "aura": 0,
        "head": 20,
        "type": 27,
        "auxType": 0,
        "body": 30,
        "mount": 0
      },
      "Mad Scientist": {
        "addons": 1,
        "feet": 97,
        "legs": 38,
        "aura": 0,
        "head": 97,
        "type": 133,
        "auxType": 0,
        "body": 0,
        "mount": 0
      },
      "Frost Troll": {
        "addons": 0,
        "feet": 0,
        "legs": 0,
        "aura": 0,
        "head": 0,
        "type": 53,
        "auxType": 0,
        "body": 0,
        "mount": 0
      },
      "Spirit of Water": {
        "addons": 0,
        "feet": 0,
        "legs": 0,
        "aura": 0,
        "head": 0,
        "type": 11,
        "auxType": 0,
        "body": 0,
        "mount": 0
      },
      "Carniphila": {
        "addons": 0,
        "feet": 0,
        "legs": 0,
        "aura": 0,
        "head": 0,
        "type": 120,
        "auxType": 0,
        "body": 0,
        "mount": 0
      },
      "Midnight Asura": {
        "addons": 1,
        "feet": 90,
        "legs": 90,
        "aura": 0,
        "head": 0,
        "type": 150,
        "auxType": 0,
        "body": 114,
        "mount": 0
      },
      "Incineron": {
        "addons": 0,
        "feet": 0,
        "legs": 0,
        "aura": 0,
        "head": 0,
        "type": 243,
        "auxType": 0,
        "body": 0,
        "mount": 0
      },
      "Drasilla": {
        "addons": 0,
        "feet": 0,
        "legs": 0,
        "aura": 0,
        "head": 0,
        "type": 34,
        "auxType": 0,
        "body": 0,
        "mount": 0
      },
      "Destroyer": {
        "addons": 0,
        "feet": 0,
        "legs": 0,
        "aura": 0,
        "head": 0,
        "type": 236,
        "auxType": 0,
        "body": 0,
        "mount": 0
      },
      "Swarmer": {
        "addons": 0,
        "feet": 0,
        "legs": 0,
        "aura": 0,
        "head": 0,
        "type": 460,
        "auxType": 0,
        "body": 0,
        "mount": 0
      },
      "Ghastly Dragon": {
        "addons": 0,
        "feet": 0,
        "legs": 0,
        "aura": 0,
        "head": 0,
        "type": 351,
        "auxType": 0,
        "body": 0,
        "mount": 0
      },
      "Sea Serpent": {
        "addons": 0,
        "feet": 0,
        "legs": 0,
        "aura": 0,
        "head": 0,
        "type": 275,
        "auxType": 0,
        "body": 0,
        "mount": 0
      },
      "Troll": {
        "addons": 0,
        "feet": 0,
        "legs": 0,
        "aura": 0,
        "head": 0,
        "type": 15,
        "auxType": 0,
        "body": 0,
        "mount": 0
      },
      "Brutal Bonelord": {
        "addons": 0,
        "feet": 0,
        "legs": 0,
        "aura": 0,
        "head": 0,
        "type": 17,
        "auxType": 0,
        "body": 0,
        "mount": 0
      },
      "Killer Caiman": {
        "addons": 0,
        "feet": 0,
        "legs": 0,
        "aura": 0,
        "head": 0,
        "type": 358,
        "auxType": 0,
        "body": 0,
        "mount": 0
      },
      "Fox": {
        "addons": 0,
        "feet": 0,
        "legs": 0,
        "aura": 0,
        "head": 0,
        "type": 1029,
        "auxType": 0,
        "body": 0,
        "mount": 0
      },
      "Dwarf Guard": {
        "addons": 0,
        "feet": 0,
        "legs": 0,
        "aura": 0,
        "head": 0,
        "type": 70,
        "auxType": 0,
        "body": 0,
        "mount": 0
      },
      "Quara Predator Scout": {
        "addons": 0,
        "feet": 0,
        "legs": 0,
        "aura": 0,
        "head": 0,
        "type": 20,
        "auxType": 0,
        "body": 0,
        "mount": 0
      },
      "Silver Rabbit": {
        "addons": 0,
        "feet": 66,
        "legs": 69,
        "aura": 0,
        "head": 69,
        "type": 262,
        "auxType": 0,
        "body": 66,
        "mount": 0
      },
      "Brutal Deepling Scout": {
        "addons": 0,
        "feet": 0,
        "legs": 0,
        "aura": 0,
        "head": 0,
        "type": 413,
        "auxType": 0,
        "body": 0,
        "mount": 0
      },
      "Fire Elemental": {
        "addons": 0,
        "feet": 0,
        "legs": 0,
        "aura": 0,
        "head": 0,
        "type": 49,
        "auxType": 0,
        "body": 0,
        "mount": 0
      },
      "Snake": {
        "addons": 0,
        "feet": 0,
        "legs": 0,
        "aura": 0,
        "head": 0,
        "type": 28,
        "auxType": 0,
        "body": 0,
        "mount": 0
      },
      "Mutated Bat": {
        "addons": 0,
        "feet": 0,
        "legs": 0,
        "aura": 0,
        "head": 0,
        "type": 307,
        "auxType": 0,
        "body": 0,
        "mount": 0
      },
      "Frazzlemaw": {
        "addons": 0,
        "feet": 0,
        "legs": 0,
        "body": 0,
        "head": 0,
        "type": 594,
        "auxType": 0,
        "aura": 0,
        "mount": 0
      },
      "Gloom Wolf": {
        "addons": 0,
        "feet": 0,
        "legs": 0,
        "aura": 0,
        "head": 0,
        "type": 716,
        "auxType": 0,
        "body": 0,
        "mount": 0
      },
      "Ogre Shaman": {
        "addons": 0,
        "feet": 0,
        "legs": 0,
        "aura": 0,
        "head": 0,
        "type": 859,
        "auxType": 0,
        "body": 0,
        "mount": 0
      },
      "Wild Warrior": {
        "addons": 0,
        "feet": 57,
        "legs": 57,
        "aura": 0,
        "head": 57,
        "type": 131,
        "auxType": 0,
        "body": 57,
        "mount": 0
      },
      "Sandcrawler": {
        "addons": 0,
        "feet": 0,
        "legs": 0,
        "aura": 0,
        "head": 0,
        "type": 350,
        "auxType": 0,
        "body": 0,
        "mount": 0
      },
      "Glooth Bandit": {
        "addons": 0,
        "feet": 114,
        "legs": 114,
        "aura": 0,
        "head": 115,
        "type": 129,
        "auxType": 0,
        "body": 80,
        "mount": 0
      },
      "Shaburak Demon": {
        "addons": 0,
        "feet": 0,
        "legs": 0,
        "aura": 0,
        "head": 0,
        "type": 417,
        "auxType": 0,
        "body": 0,
        "mount": 0
      },
      "Orc Berserker": {
        "addons": 0,
        "feet": 0,
        "legs": 0,
        "aura": 0,
        "head": 0,
        "type": 8,
        "auxType": 0,
        "body": 0,
        "mount": 0
      },
      "Grimeleech": {
        "addons": 0,
        "feet": 0,
        "legs": 0,
        "aura": 0,
        "head": 0,
        "type": 855,
        "auxType": 0,
        "body": 0,
        "mount": 0
      },
      "The Punisher": {
        "addons": 0,
        "feet": 0,
        "legs": 0,
        "aura": 0,
        "head": 0,
        "type": 236,
        "auxType": 0,
        "body": 0,
        "mount": 0
      },
      "Hellspawn": {
        "addons": 0,
        "feet": 0,
        "legs": 0,
        "aura": 0,
        "head": 0,
        "type": 322,
        "auxType": 0,
        "body": 0,
        "mount": 0
      },
      "Bat": {
        "addons": 0,
        "feet": 0,
        "legs": 0,
        "aura": 0,
        "head": 0,
        "type": 122,
        "auxType": 0,
        "body": 0,
        "mount": 0
      },
      "Crazed Beggar": {
        "addons": 3,
        "feet": 97,
        "legs": 38,
        "aura": 0,
        "head": 59,
        "type": 153,
        "auxType": 0,
        "body": 38,
        "mount": 0
      },
      "Vicious Squire": {
        "addons": 1,
        "feet": 114,
        "legs": 71,
        "aura": 0,
        "head": 97,
        "type": 131,
        "auxType": 0,
        "body": 26,
        "mount": 0
      },
      "Moohtant": {
        "addons": 0,
        "feet": 0,
        "legs": 0,
        "aura": 0,
        "head": 0,
        "type": 607,
        "auxType": 0,
        "body": 0,
        "mount": 0
      },
      "Wisp": {
        "addons": 0,
        "feet": 0,
        "legs": 0,
        "aura": 0,
        "head": 0,
        "type": 294,
        "auxType": 0,
        "body": 0,
        "mount": 0
      },
      "Stalker": {
        "addons": 0,
        "feet": 114,
        "legs": 95,
        "aura": 0,
        "head": 78,
        "type": 128,
        "auxType": 0,
        "body": 116,
        "mount": 0
      },
      "The Dreadorian": {
        "addons": 0,
        "feet": 0,
        "legs": 0,
        "aura": 0,
        "head": 0,
        "type": 234,
        "auxType": 0,
        "body": 0,
        "mount": 0
      },
      "Mutated Tiger": {
        "addons": 0,
        "feet": 0,
        "legs": 0,
        "aura": 0,
        "head": 0,
        "type": 318,
        "auxType": 0,
        "body": 0,
        "mount": 0
      },
      "Elf Arcanist": {
        "addons": 0,
        "feet": 0,
        "legs": 0,
        "aura": 0,
        "head": 0,
        "type": 63,
        "auxType": 0,
        "body": 0,
        "mount": 0
      },
      "Ogre Savage": {
        "addons": 0,
        "feet": 0,
        "legs": 0,
        "aura": 0,
        "head": 0,
        "type": 858,
        "auxType": 0,
        "body": 0,
        "mount": 0
      },
      "Baron Brute": {
        "addons": 0,
        "feet": 0,
        "legs": 0,
        "aura": 0,
        "head": 0,
        "type": 2,
        "auxType": 0,
        "body": 0,
        "mount": 0
      },
      "Minotaur Archer": {
        "addons": 0,
        "feet": 0,
        "legs": 0,
        "aura": 0,
        "head": 0,
        "type": 24,
        "auxType": 0,
        "body": 0,
        "mount": 0
      },
      "Orc Leader": {
        "addons": 0,
        "feet": 0,
        "legs": 0,
        "aura": 0,
        "head": 0,
        "type": 59,
        "auxType": 0,
        "body": 0,
        "mount": 0
      },
      "Bonelord": {
        "addons": 0,
        "feet": 0,
        "legs": 0,
        "aura": 0,
        "head": 0,
        "type": 17,
        "auxType": 0,
        "body": 0,
        "mount": 0
      },
      "Energy Elemental": {
        "addons": 0,
        "feet": 0,
        "legs": 0,
        "aura": 0,
        "head": 0,
        "type": 293,
        "auxType": 0,
        "body": 0,
        "mount": 0
      },
      "Orc Shaman": {
        "addons": 0,
        "feet": 0,
        "legs": 0,
        "aura": 0,
        "head": 0,
        "type": 6,
        "auxType": 0,
        "body": 0,
        "mount": 0
      },
      "Deer": {
        "addons": 0,
        "feet": 0,
        "legs": 0,
        "aura": 0,
        "head": 0,
        "type": 31,
        "auxType": 0,
        "body": 0,
        "mount": 0
      },
      "Elf Scout": {
        "addons": 0,
        "feet": 0,
        "legs": 0,
        "aura": 0,
        "head": 0,
        "type": 64,
        "auxType": 0,
        "body": 0,
        "mount": 0
      },
      "Toad": {
        "addons": 0,
        "feet": 0,
        "legs": 0,
        "aura": 0,
        "head": 0,
        "type": 222,
        "auxType": 0,
        "body": 0,
        "mount": 0
      },
      "Draken Warmaster": {
        "addons": 0,
        "feet": 0,
        "legs": 0,
        "aura": 0,
        "head": 0,
        "type": 334,
        "auxType": 0,
        "body": 0,
        "mount": 0
      },
      "Giant Spider": {
        "addons": 0,
        "feet": 0,
        "legs": 0,
        "aura": 0,
        "head": 0,
        "type": 38,
        "auxType": 0,
        "body": 0,
        "mount": 0
      },
      "Insect Swarm": {
        "addons": 0,
        "feet": 0,
        "legs": 0,
        "aura": 0,
        "head": 0,
        "type": 349,
        "auxType": 0,
        "body": 0,
        "mount": 0
      },
      "Dwarf Axe Warrior": {
        "addons": 0,
        "feet": 0,
        "legs": 0,
        "aura": 0,
        "head": 0,
        "type": 71,
        "auxType": 0,
        "body": 0,
        "mount": 0
      },
      "Lizard Zaogun": {
        "addons": 0,
        "feet": 0,
        "legs": 0,
        "aura": 0,
        "head": 0,
        "type": 343,
        "auxType": 0,
        "body": 0,
        "mount": 0
      },
      "Brimstone Bug": {
        "addons": 0,
        "feet": 0,
        "legs": 0,
        "aura": 0,
        "head": 0,
        "type": 352,
        "auxType": 0,
        "body": 0,
        "mount": 0
      },
      "Ghost Wolf": {
        "addons": 0,
        "feet": 0,
        "legs": 0,
        "aura": 0,
        "head": 0,
        "type": 730,
        "auxType": 0,
        "body": 0,
        "mount": 0
      },
      "Crystal Spider": {
        "addons": 0,
        "feet": 0,
        "legs": 0,
        "aura": 0,
        "head": 0,
        "type": 263,
        "auxType": 0,
        "body": 0,
        "mount": 0
      },
      "Priestess": {
        "addons": 0,
        "feet": 0,
        "legs": 0,
        "aura": 0,
        "head": 0,
        "type": 58,
        "auxType": 0,
        "body": 0,
        "mount": 0
      },
      "Wolf": {
        "addons": 0,
        "feet": 0,
        "legs": 0,
        "aura": 0,
        "head": 0,
        "type": 27,
        "auxType": 0,
        "body": 0,
        "mount": 0
      },
      "Draptor": {
        "addons": 0,
        "feet": 0,
        "legs": 0,
        "aura": 0,
        "head": 0,
        "type": 382,
        "auxType": 0,
        "body": 0,
        "mount": 0
      },
      "Rotworm": {
        "addons": 0,
        "feet": 0,
        "legs": 0,
        "aura": 0,
        "head": 0,
        "type": 26,
        "auxType": 0,
        "body": 0,
        "mount": 0
      },
      "Lancer Beetle": {
        "addons": 0,
        "feet": 0,
        "legs": 0,
        "aura": 0,
        "head": 0,
        "type": 348,
        "auxType": 0,
        "body": 0,
        "mount": 0
      },
      "Miu Furinjis": {
        "addons": 0,
        "feet": 0,
        "legs": 0,
        "aura": 0,
        "head": 20,
        "type": 241,
        "auxType": 0,
        "body": 0,
        "mount": 0
      },
      "Dog": {
        "addons": 0,
        "feet": 0,
        "legs": 0,
        "aura": 0,
        "head": 0,
        "type": 32,
        "auxType": 0,
        "body": 0,
        "mount": 0
      },
      "Rabbit": {
        "addons": 0,
        "feet": 0,
        "legs": 0,
        "aura": 0,
        "head": 0,
        "type": 74,
        "auxType": 0,
        "body": 0,
        "mount": 0
      },
      "Tarantula": {
        "addons": 0,
        "feet": 0,
        "legs": 0,
        "aura": 0,
        "head": 0,
        "type": 219,
        "auxType": 0,
        "body": 0,
        "mount": 0
      },
      "Guzzlemaw": {
        "addons": 0,
        "feet": 0,
        "legs": 0,
        "body": 0,
        "head": 0,
        "type": 584,
        "auxType": 0,
        "aura": 0,
        "mount": 0
      },
      "Waspoid": {
        "addons": 0,
        "feet": 0,
        "legs": 0,
        "aura": 0,
        "head": 0,
        "type": 462,
        "auxType": 0,
        "body": 0,
        "mount": 0
      },
      "Rat Trainer": {
        "addons": 0,
        "feet": 0,
        "legs": 0,
        "aura": 0,
        "head": 0,
        "type": 21,
        "auxType": 0,
        "body": 0,
        "mount": 0
      },
      "Lizard Dragon Priest": {
        "addons": 0,
        "feet": 0,
        "legs": 0,
        "aura": 0,
        "head": 0,
        "type": 339,
        "auxType": 0,
        "body": 0,
        "mount": 0
      },
      "Quara Mantassin Scout": {
        "addons": 0,
        "feet": 0,
        "legs": 0,
        "aura": 0,
        "head": 0,
        "type": 72,
        "auxType": 0,
        "body": 0,
        "mount": 0
      },
      "Elder Bonelord": {
        "addons": 0,
        "feet": 0,
        "legs": 0,
        "aura": 0,
        "head": 0,
        "type": 108,
        "auxType": 0,
        "body": 0,
        "mount": 0
      },
      "Thieving Squirrel": {
        "addons": 0,
        "feet": 0,
        "legs": 0,
        "aura": 0,
        "head": 0,
        "type": 274,
        "auxType": 0,
        "body": 0,
        "mount": 0
      },
      "Rot Elemental": {
        "addons": 0,
        "feet": 0,
        "legs": 0,
        "aura": 0,
        "head": 0,
        "type": 615,
        "auxType": 0,
        "body": 0,
        "mount": 0
      },
      "Lizard Legionnaire": {
        "addons": 0,
        "feet": 0,
        "legs": 0,
        "aura": 0,
        "head": 0,
        "type": 338,
        "auxType": 0,
        "body": 0,
        "mount": 0
      },
      "Fatality": {
        "addons": 0,
        "feet": 0,
        "legs": 0,
        "aura": 0,
        "head": 0,
        "type": 113,
        "auxType": 0,
        "body": 0,
        "mount": 0
      },
      "Barbarian Skullhunter": {
        "addons": 0,
        "feet": 114,
        "legs": 77,
        "aura": 0,
        "head": 0,
        "type": 254,
        "auxType": 0,
        "body": 77,
        "mount": 0
      },
      "Grimgor Guteater": {
        "addons": 0,
        "feet": 0,
        "legs": 0,
        "aura": 0,
        "head": 0,
        "type": 2,
        "auxType": 0,
        "body": 0,
        "mount": 0
      },
      "Lizard Chosen": {
        "addons": 0,
        "feet": 0,
        "legs": 0,
        "aura": 0,
        "head": 0,
        "type": 344,
        "auxType": 0,
        "body": 0,
        "mount": 0
      },
      "Massive Fire Elemental": {
        "addons": 0,
        "feet": 0,
        "legs": 0,
        "aura": 0,
        "head": 0,
        "type": 242,
        "auxType": 0,
        "body": 0,
        "mount": 0
      },
      "Mutated Pumpkin": {
        "addons": 0,
        "feet": 0,
        "legs": 0,
        "aura": 0,
        "head": 0,
        "type": 292,
        "auxType": 0,
        "body": 0,
        "mount": 0
      },
      "Elder Wyrm": {
        "addons": 0,
        "feet": 0,
        "legs": 0,
        "aura": 0,
        "head": 0,
        "type": 561,
        "auxType": 0,
        "body": 0,
        "mount": 0
      },
      "The Dark Dancer": {
        "addons": 0,
        "feet": 0,
        "legs": 0,
        "aura": 0,
        "head": 0,
        "type": 58,
        "auxType": 0,
        "body": 0,
        "mount": 0
      },
      "Crocodile": {
        "addons": 0,
        "feet": 0,
        "legs": 0,
        "aura": 0,
        "head": 0,
        "type": 119,
        "auxType": 0,
        "body": 0,
        "mount": 0
      },
      "Rustheap Golem": {
        "addons": 0,
        "feet": 0,
        "legs": 0,
        "aura": 0,
        "head": 0,
        "type": 603,
        "auxType": 0,
        "body": 0,
        "mount": 0
      },
      "Spidris": {
        "addons": 0,
        "feet": 0,
        "legs": 0,
        "aura": 0,
        "head": 0,
        "type": 457,
        "auxType": 0,
        "body": 0,
        "mount": 0
      },
      "Barbarian Brutetamer": {
        "addons": 0,
        "feet": 121,
        "legs": 95,
        "aura": 0,
        "head": 78,
        "type": 264,
        "auxType": 0,
        "body": 116,
        "mount": 0
      },
      "Dwarf Bronze Knight": {
        "addons": 0,
        "feet": 0,
        "legs": 0,
        "aura": 0,
        "head": 0,
        "type": 70,
        "auxType": 0,
        "body": 0,
        "mount": 0
      },
      "Tremorak": {
        "addons": 0,
        "feet": 0,
        "legs": 0,
        "aura": 0,
        "head": 0,
        "type": 285,
        "auxType": 0,
        "body": 0,
        "mount": 0
      },
      "Smuggler": {
        "addons": 0,
        "feet": 115,
        "legs": 113,
        "aura": 0,
        "head": 95,
        "type": 134,
        "auxType": 0,
        "body": 0,
        "mount": 0
      },
      "Blood Beast": {
        "addons": 0,
        "feet": 0,
        "legs": 0,
        "aura": 0,
        "head": 0,
        "type": 602,
        "auxType": 0,
        "body": 0,
        "mount": 0
      },
      "Ghoul": {
        "addons": 0,
        "feet": 0,
        "legs": 0,
        "aura": 0,
        "head": 0,
        "type": 18,
        "auxType": 0,
        "body": 0,
        "mount": 0
      },
      "Quara Pincher Scout": {
        "addons": 0,
        "feet": 0,
        "legs": 0,
        "aura": 0,
        "head": 0,
        "type": 77,
        "auxType": 0,
        "body": 0,
        "mount": 0
      },
      "Hellhound": {
        "addons": 0,
        "feet": 0,
        "legs": 0,
        "aura": 0,
        "head": 0,
        "type": 240,
        "auxType": 0,
        "body": 0,
        "mount": 0
      },
      "Defiler": {
        "addons": 0,
        "feet": 0,
        "legs": 0,
        "aura": 0,
        "head": 0,
        "type": 238,
        "auxType": 0,
        "body": 0,
        "mount": 0
      },
      "Choking Fear": {
        "addons": 0,
        "feet": 0,
        "legs": 0,
        "aura": 0,
        "head": 0,
        "type": 586,
        "auxType": 0,
        "body": 0,
        "mount": 0
      },
      "Bear": {
        "addons": 0,
        "feet": 0,
        "legs": 0,
        "aura": 0,
        "head": 0,
        "type": 16,
        "auxType": 0,
        "body": 0,
        "mount": 0
      },
      "Enraged Squirrel": {
        "addons": 0,
        "feet": 0,
        "legs": 0,
        "aura": 0,
        "head": 0,
        "type": 274,
        "auxType": 0,
        "body": 0,
        "mount": 0
      },
      "Draken Spellweaver": {
        "addons": 0,
        "feet": 0,
        "legs": 0,
        "aura": 0,
        "head": 0,
        "type": 340,
        "auxType": 0,
        "body": 0,
        "mount": 0
      },
      "Metal Gargoyle": {
        "addons": 0,
        "feet": 0,
        "legs": 0,
        "aura": 0,
        "head": 0,
        "type": 601,
        "auxType": 0,
        "body": 0,
        "mount": 0
      },
      "Kreebosh the Exile": {
        "addons": 0,
        "feet": 0,
        "legs": 0,
        "aura": 0,
        "head": 0,
        "type": 103,
        "auxType": 0,
        "body": 0,
        "mount": 0
      }
    },
    "customPrices": [

    ],
    "lootChannel": true,
    "trackedLoot": [

    ]
  },
  "playerList": {
    "friendList": [

    ],
    "groupMembers": true,
    "highlight": false,
    "enemyList": [

    ],
    "blackList": [

    ],
    "marks": false,
    "outfits": false
  },
  "moneyItems": [
    {
      "count": 1,
      "id": 3031
    },
    {
      "count": 1,
      "id": 3035
    },
    {
      "count": 1,
      "id": 3043
    }
  ],
  "dropper": {
    "capItems": [
      {
        "count": 1,
        "id": 21175
      }
    ],
    "useItems": [
      {
        "count": 1,
        "id": 21203
      },
      {
        "count": 1,
        "id": 14758
      }
    ],
    "enabled": true,
    "trashItems": [
      {
        "count": 1,
        "id": 283
      },
      {
        "count": 1,
        "id": 284
      },
      {
        "count": 1,
        "id": 285
      },
      {
        "count": 1,
        "id": 3583
      },
      {
        "count": 1,
        "id": 3577
      },
      {
        "count": 1,
        "id": 3578
      }
    ]
  },
  "checkVersion": 1723954579,
  "_configs": {
    "targetbot_configs": {
      "enabled": true,
      "selected": "DA-Dragons"
    },
    "cavebot_configs": {
      "enabled": true,
      "selected": "DA-Dragons"
    }
  },
  "combobot": {
    "attackLeaderTargetEnabled": false,
    "onSayEnabled": false,
    "onCastEnabled": false,
    "followLeaderEnabled": false,
    "attackItemToggle": false,
    "serverLeader": "",
    "onShootEnabled": false,
    "serverEnabled": false,
    "shootLeader": "",
    "castLeader": "",
    "sayPhrase": "",
    "sayLeader": "",
    "commandsEnabled": true,
    "serverLeaderTarget": false,
    "attackSpellEnabled": false,
    "spell": "",
    "follow": "",
    "item": 3155,
    "attack": "",
    "enabled": false,
    "serverTriggers": true
  },
  "_macros": {
    "": false,
    "Exchange money": true,
    "adeta res": true,
    "Eat Food": true,
    "pause no bless + aol": true,
    "Eat Food from Ground": false,
    "Manage Life Rings": false,
    "Use Strong Mana Potion": false,
    "rune maker": true,
    "Check Killing in the Name of Quest": false,
    "Eat Food From Ground": false
  }
}