{
  "targeting": [
    {
      "lureCount": 1,
      "rePositionAmount": 5,
      "anchorRange": 3,
      "keepDistanceRange": 1,
      "name": "Wolf, Bear, Fox, Wisp, Wasp, Snake, Sandcrawler, Lion, Skeleton, Bat, Minotaur Mage, Minotaur, Minotaur Archer, Minotaur Guard, War Wolf, Gloom Wolf, Poacher, Hunter, Deer, Rabbit, Scorpion, Cobra, Ghost Wolf, Boar, Amazon, Orc, Troll, Orc Leader, Orc Shaman, Orc Berserker, Orc Spearman, Orc Warrior, Starving Wolf",
      "faceMonster": false,
      "diamondArrows": false,
      "lure": false,
      "regex": "^wolf$|^bear$|^fox$|^wisp$|^wasp$|^snake$|^sandcrawler$|^lion$|^skeleton$|^bat$|^minotaur mage$|^minotaur$|^minotaur archer$|^minotaur guard$|^war wolf$|^gloom wolf$|^poacher$|^hunter$|^deer$|^rabbit$|^scorpion$|^cobra$|^ghost wolf$|^boar$|^amazon$|^orc$|^troll$|^orc leader$|^orc shaman$|^orc berserker$|^orc spearman$|^orc warrior$|^starving wolf$",
      "chase": false,
      "avoidAttacks": false,
      "keepDistance": false,
      "rpSafe": false,
      "closeLure": false,
      "dynamicLureDelay": false,
      "priority": 0,
      "maxDistance": 3,
      "danger": 0,
      "lureMax": 30,
      "anchor": false,
      "lureMin": 29,
      "dynamicLure": true,
      "lureDelay": 250,
      "rePosition": false,
      "closeLureAmount": 3,
      "delayFrom": 2,
      "dontLoot": true,
      "lureCavebot": false
    }
  ],
  "looting": {
    "containers": [

    ],
    "maxDanger": 100,
    "minCapacity": 0,
    "items": [

    ],
    "everyItem": false
  }
}