{
  "looting": {
    "maxDanger": 100,
    "minCapacity": 0,
    "items": [

    ],
    "containers": [

    ],
    "everyItem": false
  },
  "targeting": [
    {
      "maxDistance": 10,
      "danger": 5,
      "lureMin": 2,
      "dynamicLure": true,
      "lureDelay": 650,
      "closeLure": false,
      "closeLureAmount": 3,
      "lureCavebot": false,
      "lureCount": 1,
      "priority": 5,
      "rePositionAmount": 5,
      "anchorRange": 3,
      "keepDistanceRange": 1,
      "dynamicLureDelay": true,
      "delayFrom": 1,
      "rePosition": false,
      "dontLoot": true,
      "lure": false,
      "regex": "^ravenous lava lurker$",
      "anchor": false,
      "faceMonster": false,
      "name": "Ravenous Lava Lurker",
      "diamondArrows": false,
      "chase": false,
      "avoidAttacks": false,
      "keepDistance": false,
      "rpSafe": false,
      "lureMax": 3
    }
  ]
}