{
  "looting": {
    "maxDanger": 100,
    "minCapacity": 0,
    "everyItem": false,
    "items": [
      {
        "count": 1,
        "id": 3031
      }
    ],
    "containers": [
      {
        "count": 1,
        "id": 2854
      }
    ]
  },
  "targeting": [
    {
      "faceMonster": false,
      "priority": 5,
      "lureMax": 3,
      "anchor": false,
      "dynamicLureDelay": false,
      "rePosition": false,
      "regex": "^tarantula$",
      "lure": false,
      "rpSafe": false,
      "closeLure": false,
      "diamondArrows": false,
      "dynamicLure": false,
      "avoidAttacks": false,
      "anchorRange": 3,
      "lureMin": 1,
      "chase": true,
      "lureDelay": 250,
      "keepDistance": false,
      "closeLureAmount": 3,
      "dontLoot": false,
      "maxDistance": 3,
      "lureCavebot": false,
      "lureCount": 8,
      "danger": 5,
      "rePositionAmount": 5,
      "name": "Tarantula",
      "keepDistanceRange": 1,
      "delayFrom": 2
    },
    {
      "faceMonster": false,
      "priority": 0,
      "lureMax": 3,
      "anchor": false,
      "dynamicLureDelay": false,
      "rePosition": false,
      "regex": "^poison spider$|^centipede$|^spider$|^skunk$|^toad$|^wasp$|^terror bird$|^panda$",
      "lure": false,
      "diamondArrows": false,
      "name": "Poison Spider, Centipede, Spider, Skunk, Toad, Wasp, Terror Bird, Panda",
      "chase": false,
      "maxDistance": 3,
      "lureDelay": 250,
      "dontLoot": true,
      "lureMin": 1,
      "dynamicLure": false,
      "avoidAttacks": false,
      "closeLure": false,
      "closeLureAmount": 3,
      "delayFrom": 2,
      "keepDistance": false,
      "lureCavebot": true,
      "lureCount": 8,
      "danger": 0,
      "rePositionAmount": 5,
      "anchorRange": 3,
      "keepDistanceRange": 5,
      "rpSafe": false
    }
  ]
}