{
  "looting": {
    "items": [

    ],
    "maxDanger": 10,
    "minCapacity": 100,
    "everyItem": false,
    "containers": [

    ]
  },
  "targeting": [
    {
      "chase": false,
      "lure": false,
      "keepDistance": false,
      "priority": 1,
      "anchor": false,
      "maxDistance": 10,
      "danger": 1,
      "lureMin": 1,
      "dynamicLure": false,
      "lureDelay": 250,
      "closeLure": false,
      "closeLureAmount": 3,
      "rpSafe": false,
      "regex": "^bug$",
      "lureCavebot": true,
      "lureCount": 8,
      "name": "Bug",
      "rePositionAmount": 5,
      "anchorRange": 3,
      "keepDistanceRange": 1,
      "avoidAttacks": false,
      "lureMax": 3,
      "faceMonster": true,
      "delayFrom": 2,
      "dynamicLureDelay": false,
      "diamondArrows": false,
      "rePosition": false,
      "dontLoot": false
    },
    {
      "chase": false,
      "lure": false,
      "keepDistance": false,
      "priority": 0,
      "dontLoot": false,
      "maxDistance": 3,
      "danger": 0,
      "lureMin": 1,
      "dynamicLure": false,
      "lureDelay": 250,
      "closeLure": false,
      "closeLureAmount": 3,
      "rpSafe": false,
      "regex": "^cat$|^chicken$|^rat$",
      "lureCavebot": true,
      "lureCount": 8,
      "name": "Cat, Chicken, Rat",
      "rePositionAmount": 5,
      "anchorRange": 3,
      "keepDistanceRange": 1,
      "diamondArrows": false,
      "lureMax": 3,
      "faceMonster": false,
      "delayFrom": 2,
      "dynamicLureDelay": false,
      "anchor": false,
      "rePosition": false,
      "avoidAttacks": false
    }
  ]
}