{
  "quests": {
    "Forgotten Knowledge": {
      "id": 15,
      "completed": false,
      "missions": [

      ]
    },
    "Liquid Black Quest": {
      "id": 26,
      "completed": false,
      "missions": {
        "The First Visitor": {
          "description": "Go back to a gray island and go down a grand staircase to Fiehonja.",
          "completed": false
        }
      }
    },
    "The Secret Library": {
      "id": 57,
      "completed": false,
      "missions": {
        "Asuri - The Lament": {
          "description": "Ao pegar missao com Dedoras",
          "completed": false
        },
        "Liquid Death": {
          "description": "A large scout party of ancestors of the Njey have to deal with two enemy parties. Try to win the Deeplings over temporarity by restoring their idols: 0/9",
          "completed": false
        },
        "The Order of the Falcon": {
          "description": "It is said that an ancient order of knights once resided in Edron. The knights disappeared a long time ago but their abandoned outpost is still there. The place may yet hold some surprises.",
          "completed": false
        },
        "The Path of Defiances": {
          "description": "You have entered the path of deciances.",
          "completed": false
        }
      }
    },
    "Threatened Dreams": {
      "id": 63,
      "completed": false,
      "missions": {
        "Troubled Animals - Creation of Legends": {
          "description": "Aklestios was very happy about your support. You earned the Fae's trust and may now enter their secret realm. Search for an elemental shrine of ice, fire earth or energy to reach Feyrist.",
          "completed": true
        }
      }
    },
    "In Service of Yalahar": {
      "id": 22,
      "completed": false,
      "missions": {
        "Darashia": {
          "description": "Karith might establish a route to Darashia as soon as he sees five cities as worthy.",
          "completed": true
        },
        "Carlin": {
          "description": "Karith might establish a route to Carlin as soon as he sees five cities as worthy.",
          "completed": true
        },
        "Searoutes Around Yalahar": {
          "description": "You convicend Captain Karith of five cities which it might be worth estabilishing a ship route to and he will now sail you to seven cities in total in hope of profit.",
          "completed": true
        },
        "LibertyBay": {
          "description": "Karith might establish a route to LibertyBay as soon as he sees five cities as worthy.",
          "completed": true
        },
        "Venore": {
          "description": "Karith might establish a route to Venore as soon as he sees five cities as worthy.",
          "completed": true
        },
        "Ab'Dendriel": {
          "description": "Karith might establish a route to Ab'Dendriel as soon as he sees five cities as worthy.",
          "completed": true
        },
        "The Way to Yalahar": {
          "description": "You have delivered the research notes to Wyrdin",
          "completed": true
        }
      }
    },
    "Bigfoot's Burden": {
      "id": 7,
      "completed": false,
      "missions": {
        "Gnome Reputation": {
          "description": "Your reputation in the eyes of gnomekind is 510.\nYour standing rises at: \nReputation   30 - I \nReputation  120 - II \nReputation  480 - III \nReputation 1440 - IV \n",
          "completed": false
        },
        "Recruitment": {
          "description": "You are now a true member of the Bigfoot company.",
          "completed": true
        }
      }
    },
    "The Explorer Society": {
      "id": 45,
      "completed": false,
      "missions": {
        "Joining the Explorers": {
          "description": "Bring the pickaxe back to the Explorer Society representative.",
          "completed": true
        }
      }
    },
    "The Dream Courts": {
      "id": 44,
      "completed": false,
      "missions": {
        "The Dream Courts": {
          "description": "The fairy Myzzi asked you to help the reclusive summer and winter elves. She gave you permission to use the portals on Feyrist and Tyrsung to visit the Summer and Winter Court.",
          "completed": false
        }
      }
    },
    "The Inquisition": {
      "id": 49,
      "completed": false,
      "missions": {
        "Mission 6: The Demon Ungreez": {
          "description": "You got the the first addon of Demon Hunter Outfit! Ask Henricus for mission to unlock more addons.",
          "completed": true
        },
        "Mission 4: The Haunted Ruin": {
          "description": "You already cleaned the abandoned and haunted house in Liberty, ask Henricus for mission.",
          "completed": true
        },
        "Mission 7: The Shadow Nexus": {
          "description": "Your mission is to go to the Demon Forge and slay seven of The Ruthless Seven Minions. The Demon Forge is located in the Edron Hero Cave, through a portal after the Vampire Shield Quest.",
          "completed": false
        },
        "Mission 1: Interrogation": {
          "description": "You investigated all guards in Thais.",
          "completed": true
        },
        "Mission 5: Essential Gathering": {
          "description": "You got the Demon Hunter Outfit! Ask Henricus for mission to unlock more addons.",
          "completed": true
        },
        "Mission 3: Vampire Hunt": {
          "description": "Get back to Thais and report your mission to Henricus.",
          "completed": true
        },
        "Mission 2: Eclipse": {
          "description": "You already brought the witches' grimoire to Henricus.",
          "completed": true
        }
      }
    },
    "Killing in the Name of...": {
      "id": 23,
      "completed": false,
      "missions": {
        "Paw and Fur: Destroyers": {
          "description": "You already hunted 650/650 destroyers.",
          "completed": true
        },
        "Paw and Fur: Tromphonyte": {
          "description": "Try find its hideout and kill it.",
          "completed": false
        },
        "Paw and Fur: Sulphur Scuttler": {
          "description": "Try find its hideout and kill it.",
          "completed": false
        },
        "Paw and Fur: Big Game Hunter": {
          "description": "You are Big Game Hunter in the Paw and Fur hunting elite. You currently have 65 Paw and Fur points.",
          "completed": false
        }
      }
    },
    "Within the Tides": {
      "id": 69,
      "completed": false,
      "missions": {
        "Of Feathers and Flowers": {
          "description": "You discovered Marapur, the realm of the nagas. New  secrets and mysteries are waiting to be unveiled.",
          "completed": true
        }
      }
    },
    "Cults of Tibia": {
      "id": 10,
      "completed": false,
      "missions": {
        "Zathroth Remmants": {
          "description": "You reported your victory to Gerimor.",
          "completed": false
        }
      }
    },
    "Grave Danger": {
      "id": 17,
      "completed": false,
      "missions": {
        "08 The grave in Vengoth": {
          "description": "Find the grave in Vengoth.",
          "completed": false
        },
        "10 The grave in the old Thais temple": {
          "description": "Find the grave in the old Thais temple.",
          "completed": false
        },
        "01 The grave in Edron": {
          "description": "Find the grave in Edron's north.",
          "completed": false
        },
        "06 The grave on an isle NE of Ankrahmun": {
          "description": "Find the grave on an isle north-east of Ankrahmun.",
          "completed": false
        },
        "12 The grave on the southern ice islands": {
          "description": "Find the grave on the southern ice islands.",
          "completed": false
        },
        "03 The grave in Ghostlands": {
          "description": "Find the grave in Ghostlands.",
          "completed": false
        },
        "11 The grave at the orclands entrance": {
          "description": "Find the grave at the entrance to the Orclands.",
          "completed": false
        },
        "07 The grave in Kilmaresh": {
          "description": "Find the grave in Kilmaresh.",
          "completed": false
        },
        "09 The grave in Darashia": {
          "description": "Find the grave in Darashia.",
          "completed": false
        },
        "* Grave Danger - The Lich Knights": {
          "description": "Prevent the raising of twelve lich knights.\nSanctify the graves yet untouched and destroy any lich knights that might have been raised.\nGraves explored: 0/12",
          "completed": false
        },
        "02 The grave in the Dark cathedral": {
          "description": "Find the grave in the Dark cathedral.",
          "completed": false
        },
        "04 The grave in Cormaya": {
          "description": "Find the grave in Cormaya.",
          "completed": false
        },
        "05 The grave in the Femor Hills": {
          "description": "Find the grave in the Femor Hills.",
          "completed": false
        }
      }
    }
  }
}