{
  "loot_seller_active": false,
  "ingame_hotkeys": "macro(250, \"Eat Food From Ground\", function()\n  local player = g_game.getLocalPlayer()\n\n  if not player then\n      return\n  end\n\n  local playerPos = player:getPosition()\n\n  local tile = g_map.getTile(playerPos)\n  \n  local foodIDs = {3725, 3577, 3578, 3592, 3593, 3594, 3595, 3600, 3606, 3607, 3610, 3611, 3662, 3723, 3725, 3726, 3727}\n\n  if tile then\n    local items = tile:getItems()\n    for _, item in ipairs(items) do\n      if table.contains(foodIDs, item:getId()) then\n        g_game.use(item)\n        return\n      end\n    end\n  end\nend)",
  "last_quickloot": "butcher's axe, dreaded cleaver, giant shimmering pearl, glooth amulet, glooth blade, glooth club, mercenary sword, platinum coin, rubber cap, skull staff, terra amulet, terra hood, terra legs, terra mantle",
  "cavebot_profile": "RA-GloothBandits",
  "left_weapon_id": 3288,
  "loot_seller_cities": [
    "rathleton"
  ],
  "right_weapon_id": 7384,
  "exercise_id": 34303
}